snakemake_executor_plugin_tes/__init__.py
snakemake_executor_plugin_tes-0.1.3.dist-info/LICENSE
snakemake_executor_plugin_tes-0.1.3.dist-info/METADATA
snakemake_executor_plugin_tes-0.1.3.dist-info/WHEEL
snakemake_executor_plugin_tes-0.1.3.dist-info/RECORD
